knora/MLS-import-libraries.py
knora/__init__.py
knora/create_onto.py
knora/create_ontology.py
knora/knora-data-schema.xsd
knora/knora.py
knora/knoraConsole.py
knora/knoractl.py
knora/reset_triplestore.py
knora/test.py
knora/xml2knora.py
knora/dsplib/__init__.py
knora/dsplib/knoraConsoleModules/GroupPanel.py
knora/dsplib/knoraConsoleModules/KnDialogControl.py
knora/dsplib/knoraConsoleModules/ListPanel.py
knora/dsplib/knoraConsoleModules/OntoPanel.py
knora/dsplib/knoraConsoleModules/ProjectPanel.py
knora/dsplib/knoraConsoleModules/PropertyPanel.py
knora/dsplib/knoraConsoleModules/ResourcePanel.py
knora/dsplib/knoraConsoleModules/UserPanel.py
knora/dsplib/knoraConsoleModules/__init__.py
knora/dsplib/models/__init__.py
knora/dsplib/models/connection.py
knora/dsplib/models/group.py
knora/dsplib/models/helpers.py
knora/dsplib/models/langstring.py
knora/dsplib/models/listnode.py
knora/dsplib/models/ontology.py
knora/dsplib/models/project.py
knora/dsplib/models/propertyclass.py
knora/dsplib/models/resourceclass.py
knora/dsplib/models/user.py
knora/dsplib/utils/__init__.py
knora/dsplib/utils/knora-schema-lists.json
knora/dsplib/utils/knora-schema.json
knora/dsplib/utils/onto_commons.py
knora/dsplib/utils/onto_create_lists.py
knora/dsplib/utils/onto_create_ontology.py
knora/dsplib/utils/onto_get.py
knora/dsplib/utils/onto_validate.py
knora/dsplib/widgets/__init__.py
knora/dsplib/widgets/doublepassword.py
knora/icons/knora-py-logo.png
knora-1.3.0.dist-info/LICENSE
knora-1.3.0.dist-info/METADATA
knora-1.3.0.dist-info/WHEEL
knora-1.3.0.dist-info/entry_points.txt
knora-1.3.0.dist-info/top_level.txt
knora-1.3.0.dist-info/RECORD
