Metadata-Version: 2.1
Name: knora
Version: 1.3.0
Summary: A Python library and tools for the Knora-API
Home-page: https://github.com/dasch-swiss/knora-py
Author: Lukas Rosenthaler
Author-email: lukas.rosenthaler@dasch.swiss
License: GPLv3
Platform: UNKNOWN
Classifier: Programming Language :: Python :: 3
Classifier: License :: OSI Approved :: GNU General Public License v3 (GPLv3)
Classifier: Operating System :: OS Independent
Requires-Dist: rdflib
Requires-Dist: lxml
Requires-Dist: validators
Requires-Dist: requests
Requires-Dist: jsonschema
Requires-Dist: click
Requires-Dist: rfc3987
Requires-Dist: pystrict
Requires-Dist: wxpython
